{
    "EdgeInsiderVersions": {
        "last_updated": "October 13, 2025 05:03 PM EDT",
        "Version": [
            {
                "Channel": "current",
                "Date": "October 11, 2025 08:06 AM EDT",
                "Location": "https://msedge.sf.dl.delivery.mp.microsoft.com/filestreamingservice/files/2f00e9c7-bb79-4501-aab6-5530c081aa92/MicrosoftEdge-141.0.3537.71.pkg",
                "Version": "141.0.3537.71"
            },
            {
                "Channel": "canary",
                "Date": "October 13, 2025 01:13 PM EDT",
                "Location": "https://msedge.sf.dl.delivery.mp.microsoft.com/filestreamingservice/files/38ce4386-6e37-4e79-896c-2a025b575d73/MicrosoftEdgeCanary-143.0.3616.0.pkg",
                "Version": "143.0.3616.0"
            },
            {
                "Channel": "dev",
                "Date": "October 08, 2025 06:56 PM EDT",
                "Location": "https://msedge.sf.dl.delivery.mp.microsoft.com/filestreamingservice/files/d9cacec8-ce95-4646-a276-96a5698fc117/MicrosoftEdgeDev-142.0.3595.9.pkg",
                "Version": "142.0.3595.9"
            },
            {
                "Channel": "beta",
                "Date": "October 09, 2025 06:27 PM EDT",
                "Location": "https://msedge.sf.dl.delivery.mp.microsoft.com/filestreamingservice/files/142aa036-28b3-4b50-9a42-7e90e469c883/MicrosoftEdgeBeta-142.0.3595.11.pkg",
                "Version": "142.0.3595.11"
            }
        ]
    }
}