<?xml version="1.0" ?>
<EdgeInsiderVersions>
  <last_updated>July 25, 2025 12:16 AM EDT</last_updated>
  <Version>
    <Channel>current</Channel>
    <Date>July 16, 2025 05:06 PM EDT</Date>
    <Location>https://msedge.sf.dl.delivery.mp.microsoft.com/filestreamingservice/files/05828c72-bda8-4f2a-847a-58e65bc373b1/MicrosoftEdge-138.0.3351.95.pkg</Location>
    <Version>138.0.3351.95</Version>
  </Version>
  <Version>
    <Channel>canary</Channel>
    <Date>July 24, 2025 09:47 PM EDT</Date>
    <Location>https://msedge.sf.dl.delivery.mp.microsoft.com/filestreamingservice/files/8d6f2a2e-7c9c-470d-90f6-6a3af756d1c0/MicrosoftEdgeCanary-140.0.3456.0.pkg</Location>
    <Version>140.0.3456.0</Version>
  </Version>
  <Version>
    <Channel>dev</Channel>
    <Date>July 24, 2025 05:19 PM EDT</Date>
    <Location>https://msedge.sf.dl.delivery.mp.microsoft.com/filestreamingservice/files/ecc86bd0-4da9-4391-89b0-0b0709b497d5/MicrosoftEdgeDev-140.0.3442.1.pkg</Location>
    <Version>140.0.3442.1</Version>
  </Version>
  <Version>
    <Channel>beta</Channel>
    <Date>July 22, 2025 05:11 PM EDT</Date>
    <Location>https://msedge.sf.dl.delivery.mp.microsoft.com/filestreamingservice/files/059667d0-3fbc-40f3-8acc-074de7514617/MicrosoftEdgeBeta-139.0.3405.52.pkg</Location>
    <Version>139.0.3405.52</Version>
  </Version>
</EdgeInsiderVersions>